sphinxmark/__init__.py
sphinxmark/arial.ttf
sphinxmark/border.tpl
sphinxmark/watermark-draft.png
sphinxmark/watermark.tpl
sphinxmark-1.0.0.dist-info/LICENSE
sphinxmark-1.0.0.dist-info/METADATA
sphinxmark-1.0.0.dist-info/WHEEL
sphinxmark-1.0.0.dist-info/top_level.txt
sphinxmark-1.0.0.dist-info/RECORD
