Metadata-Version: 2.1
Name: sphinxmark
Version: 1.0.0
Summary: A Sphinx extension that enables watermarks for HTML output.
Home-page: https://github.com/kallimachos/sphinxmark
Author: Brian Moss
Author-email: kallimachos@gmail.com
License: Apache 2.0
Keywords: sphinx documentation watermark
Platform: UNKNOWN
Classifier: Development Status :: 5 - Production/Stable
Classifier: Intended Audience :: Developers
Classifier: Topic :: Documentation :: Sphinx
Classifier: Framework :: Sphinx :: Extension
Classifier: License :: OSI Approved :: Apache Software License
Classifier: Programming Language :: Python :: 3
Classifier: Programming Language :: Python :: 3.7
Classifier: Programming Language :: Python :: 3.8
Classifier: Programming Language :: Python :: 3.9
License-File: LICENSE
Requires-Dist: bottle
Requires-Dist: Pillow
Requires-Dist: sphinx
